imonke/__init__.py
imonke/account.py
imonke/admin.py
imonke/check.py
imonke/iMonkeHandler.py
imonke/iMonkeRequest.py
imonke/post.py
imonke/user.py
imonke-0.1.1.dist-info/LICENSE
imonke-0.1.1.dist-info/METADATA
imonke-0.1.1.dist-info/WHEEL
imonke-0.1.1.dist-info/top_level.txt
imonke-0.1.1.dist-info/RECORD
